MANIFEST.in
README.md
requirements.txt
setup.cfg
setup.py
test_todo.py
todo.py
completion/_todo
completion/todo-completion.bash
todo.python.egg-info/PKG-INFO
todo.python.egg-info/SOURCES.txt
todo.python.egg-info/dependency_links.txt
todo.python.egg-info/entry_points.txt
todo.python.egg-info/requires.txt
todo.python.egg-info/top_level.txt